README.md
setup.cfg
setup.py
inbot_common/__init__.py
inbot_common/py.typed
inbot_common.egg-info/PKG-INFO
inbot_common.egg-info/SOURCES.txt
inbot_common.egg-info/dependency_links.txt
inbot_common.egg-info/requires.txt
inbot_common.egg-info/top_level.txt
inbot_common/log/__init__.py
inbot_common/log/action_log.py
inbot_common/log/action_log_callback.py
inbot_common/log/action_log_model.py
inbot_common/log/auth_caller_retrieval.py
inbot_common/log/caller_retrieval.py
inbot_common/log/http_header_caller_retrieval.py
inbot_common/models/__init__.py
inbot_common/models/company.py
inbot_common/models/dashboard.py
inbot_common/models/index_map.py
inbot_common/models/industry.py
inbot_common/models/person.py
inbot_common/models/popular_table.py
inbot_common/models/post_comment.py
inbot_common/models/table.py
inbot_common/models/user.py
inbot_common/tests/__init__.py
inbot_common/tests/fixtures.py