Metadata-Version: 2.1
Name: inbot-common
Version: 0.6.0
Summary: Common code library for Inbot. Forked from amundsen-io/amundsencommon.
Home-page: https://github.com/Inbot/amundsencommon
Maintainer: Aarni Alasaarela
Maintainer-email: aarni.alasaarela@gmail.com
License: UNKNOWN
Platform: UNKNOWN
Requires-Python: >=3.6
